swarm_logic/README.md
swarm_logic/__init__.py
swarm_logic/connectors/__init__.py
swarm_logic/connectors/alchemy.py
swarm_logic/connectors/base.py
swarm_logic/connectors/dal.py
swarm_logic/connectors/json.py
swarm_logic/db.json
swarm_logic/experimental/SwarmLogicExperimental.py
swarm_logic/experimental/SwarmLogicWorker.py
swarm_logic/experimental/__init__.py
swarm_logic/swarm_logic.py
swarm_logic/utils/__init__.py
swarm_logic/utils/error_handling.py
swarmlogic-0.6.4.dist-info/LICENSE
swarmlogic-0.6.4.dist-info/WHEEL
swarmlogic-0.6.4.dist-info/METADATA
swarmlogic-0.6.4.dist-info/RECORD
